lightstream/__init__.py
lightstream/core/__init__.py
lightstream/core/constructor.py
lightstream/core/scnn.py
lightstream/core/utils.py
lightstream/models/.gitkeep
lightstream/models/__init__.py
lightstream/models/convnext/__init__.py
lightstream/models/convnext/convnext.py
lightstream/models/inceptionnext/__init__.py
lightstream/models/inceptionnext/inceptionnext.py
lightstream/models/inceptionnext/model.py
lightstream/models/resnet/__init__.py
lightstream/models/resnet/resnet.py
lightstream/modules/__init__.py
lightstream/modules/imagenet_template.py
lightstream/modules/lightningstreaming.py
lightstream/modules/streaming.py
lightstream/utils/helpers.py
lightstream-1.0.6.dist-info/METADATA
lightstream-1.0.6.dist-info/WHEEL
lightstream-1.0.6.dist-info/licenses/LICENSE
lightstream-1.0.6.dist-info/RECORD
