Metadata-Version: 2.4
Name: lightstream
Version: 1.0.6
Summary: A Pytorch lightning framework for streaming CNN's
Project-URL: Homepage, https://github.com/DIAGNijmegen/lightstream
Project-URL: Bug Tracker, https://github.com/DIAGNijmegen/lightstream/issues
Author-email: Stephan Dooper <stephan.dooper@radboudumc.nl>
License-File: LICENSE
Classifier: Operating System :: OS Independent
Classifier: Programming Language :: Python :: 3
Requires-Python: >=3.10
Requires-Dist: torch>=2.0.0
Provides-Extra: docs
Requires-Dist: mkdocs; extra == 'docs'
Requires-Dist: mkdocs-caption; extra == 'docs'
Requires-Dist: mkdocs-material; extra == 'docs'
Requires-Dist: mkdocstrings; extra == 'docs'
Requires-Dist: mkdocstrings[python]; extra == 'docs'
